pkdevtools-0.13.20260108.322.data/purelib/PKDevTools/LICENSE.txt
pkdevtools-0.13.20260108.322.data/purelib/PKDevTools/README.txt
pkdevtools-0.13.20260108.322.data/purelib/PKDevTools/__init__.py
pkdevtools-0.13.20260108.322.data/purelib/PKDevTools/release.md
pkdevtools-0.13.20260108.322.data/purelib/PKDevTools/requirements.txt
pkdevtools-0.13.20260108.322.data/purelib/PKDevTools/classes/Archiver.py
pkdevtools-0.13.20260108.322.data/purelib/PKDevTools/classes/ColorText.py
pkdevtools-0.13.20260108.322.data/purelib/PKDevTools/classes/Committer.py
pkdevtools-0.13.20260108.322.data/purelib/PKDevTools/classes/CookieHelper.py
pkdevtools-0.13.20260108.322.data/purelib/PKDevTools/classes/DBManager.py
pkdevtools-0.13.20260108.322.data/purelib/PKDevTools/classes/DatabaseSyncChecker.py
pkdevtools-0.13.20260108.322.data/purelib/PKDevTools/classes/Environment.py
pkdevtools-0.13.20260108.322.data/purelib/PKDevTools/classes/Fetcher.py
pkdevtools-0.13.20260108.322.data/purelib/PKDevTools/classes/Fileinfo.py
pkdevtools-0.13.20260108.322.data/purelib/PKDevTools/classes/FunctionTimeouts.py
pkdevtools-0.13.20260108.322.data/purelib/PKDevTools/classes/GitHubSecrets.py
pkdevtools-0.13.20260108.322.data/purelib/PKDevTools/classes/GmailReader.py
pkdevtools-0.13.20260108.322.data/purelib/PKDevTools/classes/MarketHours.py
pkdevtools-0.13.20260108.322.data/purelib/PKDevTools/classes/MenuOptions.py
pkdevtools-0.13.20260108.322.data/purelib/PKDevTools/classes/NSEMarketStatus.py
pkdevtools-0.13.20260108.322.data/purelib/PKDevTools/classes/OutputControls.py
pkdevtools-0.13.20260108.322.data/purelib/PKDevTools/classes/PKBackupRestore.py
pkdevtools-0.13.20260108.322.data/purelib/PKDevTools/classes/PKDataProvider.py
pkdevtools-0.13.20260108.322.data/purelib/PKDevTools/classes/PKDateUtilities.py
pkdevtools-0.13.20260108.322.data/purelib/PKDevTools/classes/PKGitFolderDownloader.py
pkdevtools-0.13.20260108.322.data/purelib/PKDevTools/classes/PKJoinableQueue.py
pkdevtools-0.13.20260108.322.dist-info/LICENSE
pkdevtools-0.13.20260108.322.dist-info/METADATA
pkdevtools-0.13.20260108.322.dist-info/WHEEL
pkdevtools-0.13.20260108.322.dist-info/entry_points.txt
pkdevtools-0.13.20260108.322.dist-info/top_level.txt
pkdevtools-0.13.20260108.322.dist-info/RECORD
