Metadata-Version: 2.1
Name: pkdevtools
Version: 0.13.20260108.322
Summary: A general day-to-day toolset for PKScreener repos
Home-page: https://github.com/pkjmesra/PKDevTools
Download-URL: https://github.com/pkjmesra/PKDevTools/archive/v0.13.20260108.322.zip
Author: pkjmesra
Author-email: pkjmesra@gmail.com
License: OSI Approved (MIT)
Keywords: GitHub tools,Logging,Telegram,Fetcher
Classifier: License :: OSI Approved :: MIT License
Classifier: Operating System :: Microsoft :: Windows
Classifier: Operating System :: MacOS
Classifier: Operating System :: POSIX :: Linux
Classifier: Programming Language :: Python
Classifier: Programming Language :: Python :: 3
Classifier: Programming Language :: Python :: 3.9
Classifier: Programming Language :: Python :: 3.10
Classifier: Programming Language :: Python :: 3.11
Classifier: Programming Language :: Python :: 3.12
License-File: LICENSE
Requires-Dist: aiosqlite
Requires-Dist: alive-progress
Requires-Dist: argparse
Requires-Dist: blinker
Requires-Dist: brotli
Requires-Dist: bs4
Requires-Dist: cloudscraper
Requires-Dist: cryptography
Requires-Dist: filelock
Requires-Dist: gitpython
Requires-Dist: mistletoe
Requires-Dist: pynacl
Requires-Dist: numpy
Requires-Dist: pandas
Requires-Dist: pikepdf
Requires-Dist: Pillow
Requires-Dist: PyGithub
Requires-Dist: pyotp
Requires-Dist: python-dotenv
Requires-Dist: python-telegram-bot <20.0,>=13.4
Requires-Dist: pytz
Requires-Dist: requests
Requires-Dist: requests-cache
Requires-Dist: tabulate
Requires-Dist: typing-extensions
Requires-Dist: urllib3
Requires-Dist: yfinance
